pretix_thepay/__init__.py
pretix_thepay/apps.py
pretix_thepay/payment.py
pretix_thepay/pretix_plugin_urls.py
pretix_thepay/signals.py
pretix_thepay/urls.py
pretix_thepay/views.py
pretix_thepay/locale/en/LC_MESSAGES/django.po
pretix_thepay-9.0.18.dist-info/METADATA
pretix_thepay-9.0.18.dist-info/WHEEL
pretix_thepay-9.0.18.dist-info/entry_points.txt
pretix_thepay-9.0.18.dist-info/top_level.txt
pretix_thepay-9.0.18.dist-info/RECORD
