Metadata-Version: 2.1
Name: pretix-thepay
Version: 9.0.18
Summary: The Pay payment provider for Pretix
Author-email: KrisIsNew <thepay.pretix@krisisnew.xyz>
Maintainer-email: KrisIsNew <thepay.pretix@krisisnew.xyz>
License: Apache-2.0
Project-URL: homepage, https://github.com/krisisnewxyz/pretix-thepay
Project-URL: repository, https://github.com/krisisnewxyz/pretix-thepay
Project-URL: documentation, https://github.com/krisisnewxyz/pretix-thepay
Project-URL: issues, https://github.com/krisisnewxyz/pretix-thepay/issues
Keywords: pretix,payment,thepay
Classifier: License :: OSI Approved :: Apache Software License
Classifier: Development Status :: 4 - Beta
Classifier: Intended Audience :: Developers
Classifier: Programming Language :: Python :: 3
Classifier: Programming Language :: Python :: 3.8
Classifier: Programming Language :: Python :: 3.9
Classifier: Programming Language :: Python :: 3.10
Classifier: Programming Language :: Python :: 3.11
Classifier: Programming Language :: Python :: 3.12
Requires-Python: >=3.8
Requires-Dist: pretix >=2.7.0
Requires-Dist: requests >=2.25.0
